odoo10_addon_base_geolocalize_openstreetmap-10.0.1.0.1-nspkg.pth
odoo/addons/base_geolocalize_openstreetmap/README.rst
odoo/addons/base_geolocalize_openstreetmap/__init__.py
odoo/addons/base_geolocalize_openstreetmap/__manifest__.py
odoo/addons/base_geolocalize_openstreetmap/i18n/base_geolocalize_openstreetmap.pot
odoo/addons/base_geolocalize_openstreetmap/models/__init__.py
odoo/addons/base_geolocalize_openstreetmap/models/res_partner.py
odoo/addons/base_geolocalize_openstreetmap/static/description/icon.png
odoo/addons/base_geolocalize_openstreetmap/tests/__init__.py
odoo/addons/base_geolocalize_openstreetmap/tests/test_geolocalize_openstreetmap.py
odoo10_addon_base_geolocalize_openstreetmap-10.0.1.0.1.dist-info/METADATA
odoo10_addon_base_geolocalize_openstreetmap-10.0.1.0.1.dist-info/WHEEL
odoo10_addon_base_geolocalize_openstreetmap-10.0.1.0.1.dist-info/namespace_packages.txt
odoo10_addon_base_geolocalize_openstreetmap-10.0.1.0.1.dist-info/top_level.txt
odoo10_addon_base_geolocalize_openstreetmap-10.0.1.0.1.dist-info/RECORD
