Metadata-Version: 2.1
Name: odoo10-addon-base-geolocalize-openstreetmap
Version: 10.0.1.0.1
Summary: Open street map API call to geolocalize an address
Home-page: https://github.com/OCA/geospatial
Author: ACSONE SA/NV, Odoo Community Association (OCA)
Author-email: support@odoo-community.org
License: AGPL-3
Platform: UNKNOWN
Classifier: Programming Language :: Python
Classifier: Framework :: Odoo
Classifier: License :: OSI Approved :: GNU Affero General Public License v3
Requires-Python: ~=2.7
Requires-Dist: odoo (<10.1dev,>=10.0)
Requires-Dist: requests
